structz/__init__.py
structz-0.1.1.dist-info/LICENSE
structz-0.1.1.dist-info/WHEEL
structz-0.1.1.dist-info/METADATA
structz-0.1.1.dist-info/RECORD
